stackhawk_mcp/__init__.py
stackhawk_mcp/__main__.py
stackhawk_mcp/http_server.py
stackhawk_mcp/server.py
stackhawk_mcp-1.2.0.dist-info/licenses/LICENSE
stackhawk_mcp-1.2.0.dist-info/METADATA
stackhawk_mcp-1.2.0.dist-info/WHEEL
stackhawk_mcp-1.2.0.dist-info/entry_points.txt
stackhawk_mcp-1.2.0.dist-info/top_level.txt
stackhawk_mcp-1.2.0.dist-info/RECORD
