Metadata-Version: 2.4
Name: stackhawk-mcp
Version: 1.2.0
Summary: StackHawk MCP Server for Security Analytics and Developer Integration
Author-email: "StackHawk, Inc." <support@stackhawk.com>
License-Expression: Apache-2.0
Project-URL: Homepage, https://github.com/stackhawk/stackhawk-mcp
Project-URL: Repository, https://github.com/stackhawk/stackhawk-mcp
Requires-Python: >=3.10
License-File: LICENSE
Requires-Dist: mcp>=1.0.0
Requires-Dist: httpx>=0.27.0
Requires-Dist: python-dotenv>=1.0.0
Requires-Dist: PyYAML>=6.0
Requires-Dist: jsonschema>=4.0.0
Provides-Extra: dev
Requires-Dist: pytest>=7.0.0; extra == "dev"
Requires-Dist: pytest-asyncio>=0.21.0; extra == "dev"
Requires-Dist: black>=23.0.0; extra == "dev"
Requires-Dist: mypy>=1.0.0; extra == "dev"
Dynamic: license-file
